{"inkVersion":21,"root":[["\n","ev",{"VAR?":"02_DecisionInProgress"},true,"==","/ev",[{"->":".^.b","c":true},{"b":["^ ",{"->":"TimeForDecision"},{"->":"0.7"},null]}],"nop","\n","ev",{"VAR?":"02_bIsDecisionMade"},true,"==","/ev",[{"->":".^.b","c":true},{"b":["^ ",{"->":"DecisionRevisit"},{"->":"0.15"},null]}],"nop","\n","ev",{"VAR?":"02_bIsDecisionMade"},false,"==","/ev",[{"->":".^.b","c":true},{"b":["^ ",{"->":"BeginQuest"},{"->":"0.23"},null]}],"nop","\n",["done",{"#f":5,"#n":"g-0"}],null],"done",{"BeginQuest":[["^Jesteśmy na dziedzińcu pomiędzy gmachem Mechaniki a gmachem Wydziału Instalacji Budowlanych. ","#","^portrait:GeniusLoci","/#","\n","ev","str","^Idealne miejsce na ogród.","/str","/ev",{"*":".^.c-0","flg":4},"ev","str","^Idealne miejsce na galerię plenerową.","/str","/ev",{"*":".^.c-1","flg":4},"ev","str","^Idealne miejsce na parking.","/str","/ev",{"*":".^.c-2","flg":4},"ev","str","^Idealne miejsce, żeby coś przekąsić.","/str","/ev",{"*":".^.c-3","flg":4},"ev","str","^Chętnie się dowiem, co można zrobić z tym miejscem.","/str","/ev",{"*":".^.c-4","flg":4},{"c-0":["^ ",{"->":"InitialMindMadeUp"},"\n",{"#f":5}],"c-1":["^ ",{"->":"InitialMindMadeUp"},"\n",{"#f":5}],"c-2":["^ ",{"->":"InitialMindMadeUp"},"\n",{"#f":5}],"c-3":["^ ",{"->":"InitialMindMadeUp"},"\n",{"#f":5}],"c-4":["^ ",{"->":"InitialUndecided"},"\n",{"#f":5}]}],{"#f":1}],"InitialMindMadeUp":[["^Nie wszyscy się z tym zgadzają.","\n","^Dlatego proszę, porozmawiaj z nimi. Kiedy do nich podejdziesz opowiedzą Ci jak wyobrażają sobie tę część Kampusu Centralnego i przedstawią swoje argumenty.","\n","ev","str","^Nie interesują mnie ich argumenty. Znam to miejsce i już wszystko wiem.","/str","/ev",{"*":".^.c-0","flg":20},"ev","str","^Dobrze, porozmawiam z nimi.","/str","/ev",{"*":".^.c-1","flg":20},{"c-0":["\n","ev",true,"/ev",{"VAR=":"02_DecisionInProgress","re":true},"^W porządku. ",{"->":"TimeForDecision"},"\n",{"#f":5}],"c-1":["\n",{"->":"InitialSendoff"},{"#f":5}]}],{"#f":1}],"InitialUndecided":[["^W takim razie przed Tobą kilka ciekawych rozmów. Student z wymiany zagranicznej chciałby zbudować tu niewielką knajpkę na świeżym powietrzu.","\n","^Pani mieszkająca na terenie kampusu proponuje, aby znalazła się tu zieleń. Strażnik zaś mówi, że lepszy byłby parking. I jeszcze Pan doktor. Jemu marzy się galeria plenerowa.","\n","ev","str","^W takim na mnie już pora.","/str","/ev",{"*":".^.c-0","flg":20},{"c-0":["\n",{"->":"InitialSendoff"},{"#f":5}]}],{"#f":1}],"InitialSendoff":["^Wróć do mnie, gdy skończysz rozmowy. Czekam na Twoją decyzję.","\n","ev",true,"/ev",{"VAR=":"02_DecisionInProgress","re":true},"end",{"#f":1}],"TimeForDecision":[["^Jaka jest Twoja decyzja? Mamy kilka możliwości: zieleń, gastronomia, parking i galeria. ","#","^portrait:GeniusLoci","/#","\n","ev","str","^Zostawmy zieleń.","/str","/ev",{"*":".^.c-0","flg":4},"ev","str","^Zróbmy zakątek z gastronomią.","/str","/ev",{"*":".^.c-1","flg":4},"ev","str","^Zróbmy parking.","/str","/ev",{"*":".^.c-2","flg":4},"ev","str","^Urządźmy galerię.","/str","/ev",{"*":".^.c-3","flg":4},"ev","str","^Jeszcze nie wiem.","/str","/ev",{"*":".^.c-4","flg":4},{"c-0":["\n","ev","str","^zieleń","/str","/ev",{"VAR=":"02_Decision","re":true},"ev",1,"/ev",{"VAR=":"marker","re":true},{"->":".^.^.g-0"},{"#f":5}],"c-1":["\n","ev","str","^gastronomia","/str","/ev",{"VAR=":"02_Decision","re":true},"ev",2,"/ev",{"VAR=":"marker","re":true},{"->":".^.^.g-0"},{"#f":5}],"c-2":["\n","ev","str","^parking","/str","/ev",{"VAR=":"02_Decision","re":true},"ev",3,"/ev",{"VAR=":"marker","re":true},{"->":".^.^.g-0"},{"#f":5}],"c-3":["\n","ev","str","^galeria","/str","/ev",{"VAR=":"02_Decision","re":true},"ev",4,"/ev",{"VAR=":"marker","re":true},{"->":".^.^.g-0"},{"#f":5}],"c-4":["\n","end",{"->":".^.^.g-0"},{"#f":5}],"g-0":["^A więc niech tak się stanie.","\n","ev",false,"/ev",{"VAR=":"02_DecisionInProgress","re":true},"ev",true,"/ev",{"VAR=":"02_bIsDecisionMade","re":true},"ev",{"VAR?":"marker"},{"x()":"SwitchTerrain","exArgs":1},"pop","/ev","\n","ev",{"x()":"AddToCompletedQuests"},"pop","/ev","\n","^Dziękuję, że tak szybko podjąłeś swoją decyzję! Pożegnajmy się z tym dziedzińcem i ruszajmy dalej.","\n","end",{"#f":5}]}],{"#f":1}],"DecisionRevisit":["^Dziękuję, że zająłeś się tym miejscem! ","#","^portrait:GeniusLoci","/#","\n","end",{"#f":1}],"global decl":["ev",false,{"VAR=":"00_PostInitialDialogue"},false,{"VAR=":"00_PostTutorial"},false,{"VAR=":"00_PostHowTo"},"str","^","/str",{"VAR=":"00_WhoAreYou"},"str","^","/str",{"VAR=":"00_HowOften"},false,{"VAR=":"01_DecisionInProgress"},false,{"VAR=":"01_bIsDecisionMade"},"str","^","/str",{"VAR=":"01_Decision"},false,{"VAR=":"02_DecisionInProgress"},false,{"VAR=":"02_bIsDecisionMade"},"str","^","/str",{"VAR=":"02_Decision"},false,{"VAR=":"03_DecisionInProgress"},false,{"VAR=":"03_bIsDecisionMade"},"str","^","/str",{"VAR=":"03_Decision"},false,{"VAR=":"04_DecisionInProgress"},false,{"VAR=":"04_bIsDecisionMade"},"str","^","/str",{"VAR=":"04_Decision"},false,{"VAR=":"05_DecisionInProgress"},false,{"VAR=":"05_bIsDecisionMade"},"str","^","/str",{"VAR=":"05_Decision"},false,{"VAR=":"06_DecisionInProgress"},false,{"VAR=":"06_bIsDecisionMade"},"str","^","/str",{"VAR=":"06_Decision"},false,{"VAR=":"07_DecisionInProgress"},false,{"VAR=":"07_bIsDecisionMade"},"str","^","/str",{"VAR=":"07_Decision"},false,{"VAR=":"08_DecisionInProgress"},false,{"VAR=":"08_bIsDecisionMade"},"str","^","/str",{"VAR=":"08_Decision"},false,{"VAR=":"09_DecisionInProgress"},false,{"VAR=":"09_bIsDecisionMade"},"str","^","/str",{"VAR=":"09_Decision"},0,{"VAR=":"marker"},"/ev","end",null],"#f":1}],"listDefs":{}}